libgenparser/__init__.py
libgenparser/__main__.py
libgenparser/parser.py
libgenparser/required_data.py
libgenparser/__future__/__init__.py
libgenparser/__future__/parser.py
libgenparser-1.0.0.dist-info/METADATA
libgenparser-1.0.0.dist-info/WHEEL
libgenparser-1.0.0.dist-info/top_level.txt
libgenparser-1.0.0.dist-info/RECORD
