Metadata-Version: 2.1
Name: libgenparser
Version: 1.0.0
Summary: Easy and advanced Libgen site parser
Home-page: https://github.com/BeastImran/libgenparser
Author: BeastImran
Author-email: imsalmanran789@gmail.com
License: UNKNOWN
Platform: any
Classifier: License :: OSI Approved :: MIT License
Classifier: Programming Language :: Python :: 3.6
Classifier: Programming Language :: Python :: 3.7
Classifier: Programming Language :: Python :: 3.8
Classifier: Programming Language :: Python :: 3.9
Classifier: Programming Language :: Python :: Implementation :: CPython
Classifier: Operating System :: OS Independent
Requires-Python: >=3.6
